aioopendoors/__init__.py
aioopendoors/_secrets.yaml
aioopendoors/auth.py
aioopendoors/exceptions.py
aioopendoors/model.py
aioopendoors/py.typed
aioopendoors/session.py
aioopendoors-2025.1.0.dist-info/LICENSE
aioopendoors-2025.1.0.dist-info/METADATA
aioopendoors-2025.1.0.dist-info/WHEEL
aioopendoors-2025.1.0.dist-info/RECORD
