Metadata-Version: 2.3
Name: aioopendoors
Version: 2025.1.0
Summary: Asynchronous library to communicate with the Opendoors API.
License: Apache 2.0
Author: caubios
Requires-Python: >=3.11,<4.0
Classifier: License :: Other/Proprietary License
Classifier: Programming Language :: Python :: 3
Classifier: Programming Language :: Python :: 3.11
Classifier: Programming Language :: Python :: 3.12
Classifier: Programming Language :: Python :: 3.13
Requires-Dist: aiohttp (>=3.9.3,<4.0.0)
Requires-Dist: mashumaro (>=3.12,<4.0)
Project-URL: Documentation, https://github.com/caubios/aioopendoors
Project-URL: Homepage, https://github.com/caubios/aioopendoors
Project-URL: Issues, https://github.com/caubios/aioopendoors/issues
Project-URL: Repository, https://github.com/caubios/aioopendoors
